flask_stats/__init__.py
Flask_Stats-1.0.1.dist-info/top_level.txt
Flask_Stats-1.0.1.dist-info/METADATA
Flask_Stats-1.0.1.dist-info/DESCRIPTION.rst
Flask_Stats-1.0.1.dist-info/metadata.json
Flask_Stats-1.0.1.dist-info/WHEEL
Flask_Stats-1.0.1.dist-info/RECORD
