Metadata-Version: 1.1
Name: Flask-Stats
Version: 1.0.1
Summary: A flask plugin to keep stats about your application
Home-page: https://github.com/solarnz/Flask-Stats
Author: Chris Trotman
Author-email: chris@trotman.io
License: BSD
Keywords: Flask-Stats
Platform: UNKNOWN
Classifier: Development Status :: 4 - Beta
Classifier: Environment :: Web Environment
Classifier: Intended Audience :: Developers
Classifier: License :: OSI Approved :: BSD License
Classifier: Operating System :: OS Independent
Classifier: Programming Language :: Python
Classifier: Topic :: Software Development :: Libraries :: Python Modules
